honeydew/__init__.py
honeydew/gcp.py
honeydew/gcp_bigquery.py
honeydew/gcp_logging.py
honeydew/gcp_secretmanager.py
honeydew/gcp_storage.py
honeydew/gcp_translate.py
honeydew/git.py
honeydew/mysql.py
honeydew/notification.py
honeydew/pypi.py
honeydew/ssh.py
honeydew/utils.py
honeydew-0.1.13.dist-info/LICENSE
honeydew-0.1.13.dist-info/METADATA
honeydew-0.1.13.dist-info/WHEEL
honeydew-0.1.13.dist-info/top_level.txt
honeydew-0.1.13.dist-info/RECORD
